{
    "asset_metadata": {
        "problem_type": "BINARY_CLASSIFICATION",
        "input_data_type": "STRUCTURED",
        "label_column": "Risk",
        "prediction_column": "predictedLabel",
        "probability_column": "probability",
        "categorical_columns": [
            "CheckingStatus",
            "CreditHistory",
            "LoanPurpose",
            "ExistingSavings",
            "EmploymentDuration",
            "Sex",
            "OthersOnLoan",
            "OwnsProperty",
            "InstallmentPlans",
            "Housing",
            "Job",
            "Telephone",
            "ForeignWorker"
        ],
        "feature_columns": [
            "CheckingStatus",
            "LoanDuration",
            "CreditHistory",
            "LoanPurpose",
            "LoanAmount",
            "ExistingSavings",
            "EmploymentDuration",
            "InstallmentPercent",
            "Sex",
            "OthersOnLoan",
            "CurrentResidenceDuration",
            "OwnsProperty",
            "Age",
            "InstallmentPlans",
            "Housing",
            "ExistingCreditsCount",
            "Job",
            "Dependents",
            "Telephone",
            "ForeignWorker"
        ]
    },
    "training_data_type": {
        "LoanDuration": "int",
        "LoanAmount": "int",
        "InstallmentPercent": "int",
        "CurrentResidenceDuration": "int",
        "Age": "int",
        "ExistingCreditsCount": "int",
        "Dependents": "int"
    },
    "drift_configuration": {
        "threshold": 0.10,
        "min_records": 100
    },
    "quality_configuration": {
        "threshold": 0.8,
        "min_records": 40
    },
    "fairness_configuration": {
        "features": [
            {
                "feature": "Age",
                "majority": [
                    [
                        26,
                        74
                    ]
                ],
                "minority": [
                    [
                        18,
                        25
                    ]
                ],
                "threshold": 0.8
            },
            {
                "feature": "Sex",
                "majority": [
                    "male"
                ],
                "minority": [
                    "female"
                ],
                "threshold": 0.8
            }
        ],
        "favourable_classes": [
            "No Risk"
        ],
        "unfavourable_classes": [
            "Risk"
        ],
        "min_records": 100
    },
    "mrm_configuration": {
    }
}
